hello/__init__.py
hello/hello.py
og-hello/__init__.py
og-hello/hello.py
og_template/__init__.py
og_template/hello.py
og_template-1.0.0.dist-info/METADATA
og_template-1.0.0.dist-info/WHEEL
og_template-1.0.0.dist-info/top_level.txt
og_template-1.0.0.dist-info/RECORD
