Metadata-Version: 2.1
Name: og-template
Version: 1.0.0
Summary: Template for python package
Home-page: 
Author: og
Author-email: anonymous@gmail.com
License: UNKNOWN
Platform: UNKNOWN
Classifier: Programming Language :: Python :: 3
Classifier: License :: OSI Approved :: MIT License
Classifier: Operating System :: OS Independent
Requires-Python: >=3.0
